database.py
mcp_server_enhanced.py
memory_manager.py
kiro_mcp_memory-1.2.1.dist-info/licenses/LICENSE
kiro_mcp_memory-1.2.1.dist-info/METADATA
kiro_mcp_memory-1.2.1.dist-info/WHEEL
kiro_mcp_memory-1.2.1.dist-info/entry_points.txt
kiro_mcp_memory-1.2.1.dist-info/top_level.txt
kiro_mcp_memory-1.2.1.dist-info/RECORD
