Metadata-Version: 2.4
Name: kiro-mcp-memory
Version: 1.2.1
Summary: Enhanced MCP server for Kiro memory and task management with AI-powered features
Home-page: https://github.com/cbunting99/kiro-mcp-memory
Author: cbunting99
Author-email: cbunting99 <cbunting99@users.noreply.github.com>
Maintainer-email: cbunting99 <cbunting99@users.noreply.github.com>
License-Expression: MIT
Project-URL: Homepage, https://github.com/cbunting99/kiro-mcp-memory
Project-URL: Repository, https://github.com/cbunting99/kiro-mcp-memory
Project-URL: Issues, https://github.com/cbunting99/kiro-mcp-memory/issues
Project-URL: Documentation, https://github.com/cbunting99/kiro-mcp-memory#readme
Keywords: mcp,memory,ai,task-management,knowledge-graph,semantic-search
Classifier: Development Status :: 4 - Beta
Classifier: Intended Audience :: Developers
Classifier: Operating System :: OS Independent
Classifier: Programming Language :: Python :: 3
Classifier: Programming Language :: Python :: 3.8
Classifier: Programming Language :: Python :: 3.9
Classifier: Programming Language :: Python :: 3.10
Classifier: Programming Language :: Python :: 3.11
Classifier: Programming Language :: Python :: 3.12
Classifier: Topic :: Software Development :: Libraries :: Python Modules
Classifier: Topic :: Database
Classifier: Topic :: Scientific/Engineering :: Artificial Intelligence
Requires-Python: >=3.8
License-File: LICENSE
Requires-Dist: fastmcp>=2.10.5
Requires-Dist: python-dotenv>=1.0.0
Requires-Dist: sentence-transformers>=2.2.0
Requires-Dist: numpy>=1.21.0
Requires-Dist: scipy>=1.7.0
Requires-Dist: filelock>=3.0.0
Provides-Extra: dev
Requires-Dist: pytest>=7.0.0; extra == "dev"
Requires-Dist: pytest-asyncio>=0.21.0; extra == "dev"
Requires-Dist: black>=22.0.0; extra == "dev"
Requires-Dist: isort>=5.0.0; extra == "dev"
Requires-Dist: flake8>=4.0.0; extra == "dev"
Dynamic: author
Dynamic: home-page
Dynamic: license-file
Dynamic: requires-python
